vote/voter_case.v
module voter_case (I, O);
input [3:0] I; // I 4 men
output [3:1] O; // O Result
reg [3:1] O; 

always@ (I)    
    case (I)
        4'b0000 : O[3] = 1;
        4'b0001 : O[3] = 1;
        4'b0010 : O[3] = 1;
        4'b0100 : O[3] = 1;
        4'b1000 : O[3] = 1;
        default : O[3] = 0;
    endcase

always@ (I)    
    case (I)
        4'b0011 : O[2] = 1;
        4'b0101 : O[2] = 1;
        4'b0110 : O[2] = 1;
        4'b1001 : O[2] = 1;
        4'b1010 : O[2] = 1;
        4'b1100 : O[2] = 1;
        default : O[2] = 0;
    endcase

always@ (I) 
    case (I)
        4'b1110 : O[1] = 1;
        4'b1101 : O[1] = 1;
        4'b1011 : O[1] = 1;
        4'b0111 : O[1] = 1;
        4'b1111 : O[1] = 1;
        default : O[1] = 0;
    endcase

endmodule

vote/voter_tb.v
module voter_tb;
reg [3:0] I;
wire [3:1] O;
voter_case voter_1(.I(I), .O(O));

initial 
    begin
        #10 I = 4'b0000;
        #10 I = 4'b0001;
        #10 I = 4'b0010;
        #10 I = 4'b0011;
        #10 I = 4'b0100;
        #10 I = 4'b0101;
        #10 I = 4'b0110;
        #10 I = 4'b0111;
        #10 I = 4'b1000;
        #10 I = 4'b1001;
        #10 I = 4'b1010;
        #10 I = 4'b1011;
        #10 I = 4'b1100;
        #10 I = 4'b1101;
        #10 I = 4'b1110;
        #10 I = 4'b1111;
        #10 $finish;
    end

initial begin
    $dumpfile("voter_tb.vcd");
    $dumpvars(0, voter_tb);
end
endmodule

vote/voter_tb.vcd
$date
	Sat Apr 16 22:26:18 2022
$end
$version
	Icarus Verilog
$end
$timescale
	1s
$end
$scope module voter_tb $end
$var wire 3 ! O [3:1] $end
$var reg 4 " I [3:0] $end
$scope module voter_1 $end
$var wire 4 # I [3:0] $end
$var reg 3 $ O [3:1] $end
$upscope $end
$upscope $end
$enddefinitions $end
#0
$dumpvars
bx $
bx #
bx "
bx !
$end
#10
b100 !
b100 $
b0 "
b0 #
#20
b1 "
b1 #
#30
b10 "
b10 #
#40
b10 !
b10 $
b11 "
b11 #
#50
b100 !
b100 $
b100 "
b100 #
#60
b10 !
b10 $
b101 "
b101 #
#70
b110 "
b110 #
#80
b1 !
b1 $
b111 "
b111 #
#90
b100 !
b100 $
b1000 "
b1000 #
#100
b10 !
b10 $
b1001 "
b1001 #
#110
b1010 "
b1010 #
#120
b1 !
b1 $
b1011 "
b1011 #
#130
b10 !
b10 $
b1100 "
b1100 #
#140
b1 !
b1 $
b1101 "
b1101 #
#150
b1110 "
b1110 #
#160
b1111 "
b1111 #
