BCD/BCD.v
`timescale 1ns / 1ps


module BCD(clk,rst,load,data,disp);
input clk;
input rst;
input load;
input [3:0] data;
output [7:0] disp;
reg [3:0] Q1;
reg [7:0] disp;

always@(posedge clk)
begin
   if(!rst)
      Q1<=0;
   else if(Q1==9)
      Q1<=0;
   else if(load)
      Q1<=data;
   else 
      Q1<=Q1+1;
end

always@(Q1)
   case(Q1)
      4'b0000:disp=8'b11000000;
      4'b0001:disp=8'b11111001;
      4'b0010:disp=8'b10100100;
      4'b0011:disp=8'b10110000;
      4'b0100:disp=8'b10011001;
      4'b0101:disp=8'b10010010;
      4'b0110:disp=8'b10000010;
      4'b0111:disp=8'b11111000;
      4'b1000:disp=8'b10000000;
      4'b1001:disp=8'b10010000;
   endcase
endmodule

BCD/BCD_tb.v
`timescale 1ns/1ps
module BCD_tb;
  reg clk;
  reg rst;
  reg load;
  reg [3:0] data;
  wire [7:0] disp;
  wire [3:0] Q1;

  parameter OFFSET = 0;
  parameter PERIOD = 20;
  parameter real DUTY_CYCLE = 0.5;

  initial
    begin
      #OFFSET;
      forever
        begin
          clk = 1'b0;
          #(PERIOD-(PERIOD*DUTY_CYCLE)) clk = 1'b1;
          #(PERIOD*DUTY_CYCLE);
      	end
      end
      initial begin
        rst = 1'b0;
        load=1'b0;
        data=4'b0101;
        #20 rst= 1'b1;
        #200 load= 1'b1;
        #201 load= 1'b0;
        #1000 $finish;
      end
      initial begin
      $dumpfile("BCD.vcd");
      $dumpvars(0, BCD_tb);
    end

  BCD BCD_tb (.clk(clk),.rst(rst),.load(load),.data(data),.disp(disp));
endmodule

BCD/BCD.vcd
$date
	Tue Jun 14 19:35:43 2022
$end
$version
	Icarus Verilog
$end
$timescale
	1ps
$end
$scope module BCD_tb $end
$scope module BCD_tb $end
$var wire 1 ! clk $end
$var wire 4 " data [3:0] $end
$var wire 1 # load $end
$var wire 1 $ rst $end
$var reg 4 % Q1 [3:0] $end
$var reg 8 & disp [7:0] $end
$upscope $end
$upscope $end
$enddefinitions $end
#0
$dumpvars
bx &
bx %
0$
0#
b101 "
0!
$end
#10000
b11000000 &
b0 %
1!
#20000
0!
1$
#30000
b11111001 &
b1 %
1!
#40000
0!
#50000
b10100100 &
b10 %
1!
#60000
0!
#70000
b10110000 &
b11 %
1!
#80000
0!
#90000
b10011001 &
b100 %
1!
#100000
0!
#110000
b10010010 &
b101 %
1!
#120000
0!
#130000
b10000010 &
b110 %
1!
#140000
0!
#150000
b11111000 &
b111 %
1!
#160000
0!
#170000
b10000000 &
b1000 %
1!
#180000
0!
#190000
b10010000 &
b1001 %
1!
#200000
0!
#210000
b11000000 &
b0 %
1!
#220000
0!
1#
#230000
b10010010 &
b101 %
1!
#240000
0!
#250000
1!
#260000
0!
#270000
1!
#280000
0!
#290000
1!
#300000
0!
#310000
1!
#320000
0!
#330000
1!
#340000
0!
#350000
1!
#360000
0!
#370000
1!
#380000
0!
#390000
1!
#400000
0!
#410000
1!
#420000
0!
#421000
0#
#430000
b10000010 &
b110 %
1!
#440000
0!
#450000
b11111000 &
b111 %
1!
#460000
0!
#470000
b10000000 &
b1000 %
1!
#480000
0!
#490000
b10010000 &
b1001 %
1!
#500000
0!
#510000
b11000000 &
b0 %
1!
#520000
0!
#530000
b11111001 &
b1 %
1!
#540000
0!
#550000
b10100100 &
b10 %
1!
#560000
0!
#570000
b10110000 &
b11 %
1!
#580000
0!
#590000
b10011001 &
b100 %
1!
#600000
0!
#610000
b10010010 &
b101 %
1!
#620000
0!
#630000
b10000010 &
b110 %
1!
#640000
0!
#650000
b11111000 &
b111 %
1!
#660000
0!
#670000
b10000000 &
b1000 %
1!
#680000
0!
#690000
b10010000 &
b1001 %
1!
#700000
0!
#710000
b11000000 &
b0 %
1!
#720000
0!
#730000
b11111001 &
b1 %
1!
#740000
0!
#750000
b10100100 &
b10 %
1!
#760000
0!
#770000
b10110000 &
b11 %
1!
#780000
0!
#790000
b10011001 &
b100 %
1!
#800000
0!
#810000
b10010010 &
b101 %
1!
#820000
0!
#830000
b10000010 &
b110 %
1!
#840000
0!
#850000
b11111000 &
b111 %
1!
#860000
0!
#870000
b10000000 &
b1000 %
1!
#880000
0!
#890000
b10010000 &
b1001 %
1!
#900000
0!
#910000
b11000000 &
b0 %
1!
#920000
0!
#930000
b11111001 &
b1 %
1!
#940000
0!
#950000
b10100100 &
b10 %
1!
#960000
0!
#970000
b10110000 &
b11 %
1!
#980000
0!
#990000
b10011001 &
b100 %
1!
#1000000
0!
#1010000
b10010010 &
b101 %
1!
#1020000
0!
#1030000
b10000010 &
b110 %
1!
#1040000
0!
#1050000
b11111000 &
b111 %
1!
#1060000
0!
#1070000
b10000000 &
b1000 %
1!
#1080000
0!
#1090000
b10010000 &
b1001 %
1!
#1100000
0!
#1110000
b11000000 &
b0 %
1!
#1120000
0!
#1130000
b11111001 &
b1 %
1!
#1140000
0!
#1150000
b10100100 &
b10 %
1!
#1160000
0!
#1170000
b10110000 &
b11 %
1!
#1180000
0!
#1190000
b10011001 &
b100 %
1!
#1200000
0!
#1210000
b10010010 &
b101 %
1!
#1220000
0!
#1230000
b10000010 &
b110 %
1!
#1240000
0!
#1250000
b11111000 &
b111 %
1!
#1260000
0!
#1270000
b10000000 &
b1000 %
1!
#1280000
0!
#1290000
b10010000 &
b1001 %
1!
#1300000
0!
#1310000
b11000000 &
b0 %
1!
#1320000
0!
#1330000
b11111001 &
b1 %
1!
#1340000
0!
#1350000
b10100100 &
b10 %
1!
#1360000
0!
#1370000
b10110000 &
b11 %
1!
#1380000
0!
#1390000
b10011001 &
b100 %
1!
#1400000
0!
#1410000
b10010010 &
b101 %
1!
