random/random.v
module random(clk,clr,X);
  input clk;
  input clr;
  output X;
  reg[2:0] Q;        //3個寄存器
  assign X=Q[0];     //輸出連結
always@(negedge clk or posedge clr)
  if(clr)begin
    Q<=4'b1111;      //不0000
  end
  else begin
    Q[1:0]<=Q[2:1];
    Q[2]<=Q[2]+Q[0];
end
endmodule

random/random_tb.v
module random_tb;
  reg clk_tb,clr_tb;
  wire X_tb;
  random random_1(.clk(clk_tb),.clr(clr_tb),.X(X_tb));
initial begin
  clk_tb=0;
  clr_tb=1;
end
always begin
  #5 clk_tb=~clk_tb;
end
initial begin
  #5 clr_tb=1;
  #5 clr_tb=0;
  #140 $finish;
end
initial begin
  $dumpfile("random.vcd");
  $dumpvars(0,random_tb);
end
endmodule

random/random.vcd
$date
	Thu May 19 23:58:16 2022
$end
$version
	Icarus Verilog
$end
$timescale
	1s
$end
$scope module random_tb $end
$var wire 1 ! X_tb $end
$var reg 1 " clk_tb $end
$var reg 1 # clr_tb $end
$scope module random_1 $end
$var wire 1 " clk $end
$var wire 1 # clr $end
$var wire 1 ! X $end
$var reg 3 $ Q [2:0] $end
$upscope $end
$upscope $end
$enddefinitions $end
#0
$dumpvars
b111 $
1#
0"
1!
$end
#5
1"
#10
b11 $
0#
0"
#15
1"
#20
b101 $
0"
#25
1"
#30
0!
b10 $
0"
#35
1"
#40
1!
b1 $
0"
#45
1"
#50
0!
b100 $
0"
#55
1"
#60
b110 $
0"
#65
1"
#70
1!
b111 $
0"
#75
1"
#80
b11 $
0"
#85
1"
#90
b101 $
0"
#95
1"
#100
0!
b10 $
0"
#105
1"
#110
1!
b1 $
0"
#115
1"
#120
0!
b100 $
0"
#125
1"
#130
b110 $
0"
#135
1"
#140
1!
b111 $
0"
#145
1"
#150
b11 $
0"
